README
setup.py
easyhtml/__init__.py
easyhtml/dom.py
easyhtml/parser.py
easyhtml.egg-info/PKG-INFO
easyhtml.egg-info/SOURCES.txt
easyhtml.egg-info/dependency_links.txt
easyhtml.egg-info/top_level.txt