Metadata-Version: 1.0
Name: easyhtml
Version: 1.2.0
Summary: A package that provides an API to create a DOM of HTML documents and access to its elements
Home-page: http://easyhtml.sourceforge.net/
Author: Taras Gaidukov
Author-email: kemaweyan@gmail.com
License: GPLv3
Keywords: html dom parser
Platform: UNKNOWN
